migrate_code/__about__.py
migrate_code/__init__.py
migrate_code/cli.py
migrate_code/cli_utils.py
migrate_code/git_utils.py
migrate_code/migration.py
migrate_code/models.py
migrate_code/types.py
migrate_code-1.0.0.dist-info/METADATA
migrate_code-1.0.0.dist-info/WHEEL
migrate_code-1.0.0.dist-info/entry_points.txt
migrate_code-1.0.0.dist-info/licenses/LICENSE.txt
migrate_code-1.0.0.dist-info/RECORD
