Metadata-Version: 2.1
Name: migrate-code
Version: 1.0.0
Summary: Programmatically create and revert a sequence of commits
Project-URL: Documentation, https://github.com/maresb/migrate-code#readme
Project-URL: Issues, https://github.com/maresb/migrate-code/issues
Project-URL: Source, https://github.com/maresb/migrate-code
Author-email: Ben Mares <services-migrate-code@tensorial.com>
License-File: LICENSE.txt
Classifier: Programming Language :: Python :: 3.10
Classifier: Programming Language :: Python :: Implementation :: CPython
Requires-Python: >=3.10
Requires-Dist: pydantic
Requires-Dist: typer
